{
    "title": "취득세 과세표준 기준",
    "lawIds": [
        "001649"
    ],
    "counselId": 98970,
    "createdAt": "2025-12-12T08:31:12.148498",
    "fieldLarge": "지방세",
    "articleKeys": [
        "0010021"
    ],
    "lawArticles": [
        "제 10조의 21"
    ],
    "documentType": "counsel",
    "lawArticleKeys": [
        "0010021"
    ],
    "lawArticlePairs": [
        "001649:0010021"
    ]
}

제목: 취득세 과세표준 기준1
내용: 상속으로 상가를 취득할 경우 과세표준은 시가표준액으로 알고 있습니다. A씨의 경우 상가의 시가표준액가 감정가액보다 오히려 높은 상황입니다. 그런데, 상속시 예외규정이 있는 것은 “혜택”의 취지로 보이는데요 이때, 감정평가를 받아 시가인정액(감정평가 금액)으로 신고하는 것이 가능한가요?
답변: 1. 질의쟁점 아래의 사실관계에서 감정평가를 받아 시가인정액(감정평가 금액)으로 신고하는 것이 가능한가요? [사실관계] 상속으로 상가를 취득할 경우 과세표준은 시가표준액으로 알고 있습니다. A씨의 경우 상가의 시가표준액가 감정가액보다 오히려 높은 상황입니다.그런데, 상속시 예외규정이 있는 것은 “혜택”의 취지로 보이는데요 2. 관련규정 [지방세법] 제10조의2(무상취득의 경우 과세표준) 1 부동산등을 무상취득하는 경우 제10조에 따른 취득 당시의 가액(이하 “취득당시가액”이라 한다)은 취득시기 현재 불특정 다수인 사이에 자유롭게 거래가 이루어지는 경우 통상적으로 성립된다고 인정되는 가액(매매사례가액, 감정가액, 공매가액 등 대통령령으로 정하는 바에 따라 시가로 인정되는 가액을 말하며, 이하 “시가인정액”이라 한다)으로 한다. ② 제1항에도 불구하고 다음 각 호의 경우에는 해당 호에서 정하는 가액을 취득당시가액으로 한다. ①. 상속에 따른 무상취득의 경우: 제4조에 따른 시가표준액 3. 검토회신 지방세법 제10조의2제1항의 규정에 의거 부동산등을 무상취득하는 경우 취득 당시의 가액은 취득시기 현재 불특정 다수인 사이에 자유롭게 거래가 이루어지는 경우 통상적으로 성립된다고 인정되는 가액으로 하나 상속에 따른 무상취득의 경우에는 시가표준액에을 취득당시가액으로 하는 것입니다, 귀문의 경우 사실관계가 명확하지 아니하나 시가표준액가 감정가액보다 오히려 높은 상황에서는 현재 해석례를 볼 때 시가표준액을 적용하는 것이 원칙이나 시가표준액이 현저하게 불합리한 경우라면 감정가액이 객관적 가치를 입증하는 정당한 시가를 주장할 수가 있는 것입니다.(끝) 2025년 핵심실무 지방세해설(전동흔 저)를 근거하여 참고용으로 설명하였으며 더 세부적인 설명이 필요한 부분은 아래의 참고문헌을 참조하기 바랍니다. [참고문헌] 2025년 핵심실무 지방세해설(전동흔 저), ㈜ 조세영화통람사, 지방세법 취득세 과세표준 부분을 참조하시기 바람
연관 법령: 제 10조의 21